requires.io-0.2.6.dist-info/DESCRIPTION.rst
requires.io-0.2.6.dist-info/METADATA
requires.io-0.2.6.dist-info/RECORD
requires.io-0.2.6.dist-info/WHEEL
requires.io-0.2.6.dist-info/entry_points.txt
requires.io-0.2.6.dist-info/metadata.json
requires.io-0.2.6.dist-info/top_level.txt
requires.io-0.2.6.dist-info/zip-safe
requires_io/__init__.py
requires_io/api.py
requires_io/commands.py
requires_io/consts.py
requires_io/draw.py
requires_io/tests.py
